receptor_germline_tools/__init__.py
receptor_germline_tools/add_germline_annotations.py
receptor_germline_tools/annotate_rearrangements.py
receptor_germline_tools/convert_fasta_labels.py
receptor_germline_tools/create_fasta.py
receptor_germline_tools/germline_utils.py
receptor_germline_tools-0.0.4.dist-info/LICENSE
receptor_germline_tools-0.0.4.dist-info/METADATA
receptor_germline_tools-0.0.4.dist-info/WHEEL
receptor_germline_tools-0.0.4.dist-info/entry_points.txt
receptor_germline_tools-0.0.4.dist-info/top_level.txt
receptor_germline_tools-0.0.4.dist-info/RECORD
